post/__init__.py
post/admin.py
post/apps.py
post/models.py
post/tests.py
post/views.py
post/templatetags/__init__.py
post/templatetags/post_tags.py
post/templatetags/__pycache__/__init__.cpython-37.pyc
post/templatetags/__pycache__/__init__.cpython-39.pyc
post/templatetags/__pycache__/post_tags.cpython-37.pyc
post/templatetags/__pycache__/post_tags.cpython-39.pyc
django_easy_blog-1.0.3.dist-info/LICENSE
django_easy_blog-1.0.3.dist-info/METADATA
django_easy_blog-1.0.3.dist-info/WHEEL
django_easy_blog-1.0.3.dist-info/top_level.txt
django_easy_blog-1.0.3.dist-info/RECORD
